coinflex_ws/__init__.py
coinflex_ws/coinflex_ws.py
coinflex_ws-0.1.1.dist-info/LICENSE.txt
coinflex_ws-0.1.1.dist-info/METADATA
coinflex_ws-0.1.1.dist-info/WHEEL
coinflex_ws-0.1.1.dist-info/top_level.txt
coinflex_ws-0.1.1.dist-info/RECORD
