Metadata-Version: 2.1
Name: coinflex-ws
Version: 0.1.1
Summary: Simple WebSocket adapter for CoinFLEX's WebSocket API
Home-page: UNKNOWN
Author: Philipp Chvetsov
Author-email: philipp.c@coinflex.com
License: MIT
Platform: UNKNOWN
Classifier: Programming Language :: Python :: 3
Classifier: License :: OSI Approved :: MIT License
Classifier: Operating System :: OS Independent
Requires-Python: >=3.6
Requires-Dist: websocket-client (==0.53.0)
